{
  "type": "FeatureCollection",
  "features": [
    {
      "type": "Feature",
      "properties": {
        "marker-color": "#ff0000",
        "marker-size": "small",
        "marker-symbol": "",
        "description": "Le contact basal: alternance d'amphibolites et de gneiss plagioclasiques foliés. Cette formation correspond à la partie supérieure du complexe filonien dans lequel les filons basaltiques alternaient avec des plagiogranites. L'ensemble a été intensément déformé lors de l'obduction de l'ophiolite.",
        "name": "Arrêt 1"
      },
      "geometry": {
        "type": "Point",
        "coordinates": [
          5.877388888888889,
          45.10873333333333
        ]
      }
    },
    {
      "type": "Feature",
      "properties": {
        "marker-color": "#ff0000",
        "marker-size": "small",
        "marker-symbol": "",
        "description": "Le complexe filonien: les filons de basalte doléritique à phénocristaux de plagioclase et bordures figées sont bien visibles. Ils sont intrusifs dans des gabbros foliés leucocrates",
        "name": "Arrêt 2",
        "cNT": "45° 6' 35,450\" N",
        "cET": "5° 52' 46,620\" E",
        "cND": "45,1098472222222",
        "cED": "5,87961666666667"
      },
      "geometry": {
        "type": "Point",
        "coordinates": [
          5.879616666666667,
          45.10984722222222
        ]
      }
    },
    {
      "type": "Feature",
      "properties": {
        "marker-color": "#7e7e7e",
        "marker-size": "medium",
        "marker-symbol": "",
        "description": 0,
        "pName": "Arrêt 3",
        "cNT": "45° 7' 13,110\" N",
        "cET": "5° 53' 54,260\" E",
        "cND": "45,1203083333333",
        "cED": "5,89840555555555"
      },
      "geometry": {
        "type": "Point",
        "coordinates": [
          5.898405555555555,
          45.120308333333334
        ]
      }
    },
    {
      "type": "Feature",
      "properties": {
        "marker-color": "#7e7e7e",
        "marker-size": "medium",
        "marker-symbol": "",
        "description": 0,
        "pName": "Arrêt 6",
        "cNT": "45° 7' 36,140\" N",
        "cET": "5° 54' 47,660\" E",
        "cND": "45,1267055555556",
        "cED": "5,91323888888889"
      },
      "geometry": {
        "type": "Point",
        "coordinates": [
          5.913238888888889,
          45.12670555555555
        ]
      }
    },
    {
      "type": "Feature",
      "properties": {
        "marker-color": "#7e7e7e",
        "marker-size": "medium",
        "marker-symbol": "",
        "description": 0,
        "pName": "Arrêt 4",
        "cNT": "45° 7' 31,110\" N",
        "cET": "5° 54' 5,230\" E",
        "cND": "45,1253083333333",
        "cED": "5,90145277777778"
      },
      "geometry": {
        "type": "Point",
        "coordinates": [
          5.901452777777778,
          45.12530833333334
        ]
      }
    },
    {
      "type": "Feature",
      "properties": {
        "marker-color": "#7e7e7e",
        "marker-size": "medium",
        "marker-symbol": "",
        "description": 0,
        "pName": "Arrêt 5",
        "cNT": "45° 7' 33,860\" N",
        "cET": "5° 54' 37,460\" E",
        "cND": "45,1260722222222",
        "cED": "5,91040555555556"
      },
      "geometry": {
        "type": "Point",
        "coordinates": [
          5.910405555555556,
          45.12607222222222
        ]
      }
    },
    {
      "type": "Feature",
      "properties": {
        "marker-color": "#7e7e7e",
        "marker-size": "medium",
        "marker-symbol": "",
        "description": 0,
        "pName": "Arrêt 7",
        "cNT": "45° 7' 25,650\" N",
        "cET": "5° 54' 35,040\" E",
        "cND": "45,1237916666667",
        "cED": "5,90973333333333"
      },
      "geometry": {
        "type": "Point",
        "coordinates": [
          5.909733333333334,
          45.12379166666667
        ]
      }
    },
    {
      "type": "Feature",
      "properties": {
        "marker-color": "#7e7e7e",
        "marker-size": "medium",
        "marker-symbol": "",
        "description": 0,
        "pName": "Arrêt 8",
        "cNT": "45° 6' 52,700\" N",
        "cET": "5° 54' 13,210\" E",
        "cND": "45,1146388888889",
        "cED": "5,90366944444444"
      },
      "geometry": {
        "type": "Point",
        "coordinates": [
          5.903669444444445,
          45.11463888888889
        ]
      }
    }
  ]
}
